asr_eval/__init__.py
asr_eval-0.0.1.dist-info/METADATA
asr_eval-0.0.1.dist-info/WHEEL
asr_eval-0.0.1.dist-info/top_level.txt
asr_eval-0.0.1.dist-info/RECORD
