Metadata-Version: 2.4
Name: asr_eval
Version: 0.0.1
Summary: Evaluation tools for Automatic Speech Recognition
Author-email: Oleg Sedukhin <sedukhin@sibnn.ai>
Requires-Python: >=3.12
